zipdist/__init__.py
zipdist/conversions.py
zipdist/extraction.py
zipdist/zip.py
zipdist/zip2.py
zipdist/tests/__init__.py
zipdist/tests/test_conversions.py
zipdist/tests/test_extraction.py
zipdist/tests/test_tar.py
zipdist/tests/test_zip.py
zipdist/tests/test_zip2.py
zipdist-0.1.5.dist-info/LICENSE
zipdist-0.1.5.dist-info/METADATA
zipdist-0.1.5.dist-info/WHEEL
zipdist-0.1.5.dist-info/top_level.txt
zipdist-0.1.5.dist-info/RECORD
