Metadata-Version: 2.1
Name: zipdist
Version: 0.1.5
Summary: Tidy saving and loading of Numpy and Pandas object attributes
Home-page: https://github.com/kmayerb/zipdist
Author: Koshlan Mayer-Blackwell
Author-email: kmayerbl@fredhutch.org
Maintainer: Koshlan Mayer-Blackwell
Maintainer-email: kmayerbl@fredhutch.org
License: MIT
Platform: UNKNOWN
Requires-Dist: numpy (>=1.18.1)
Requires-Dist: pandas (>=0.24.2)
Requires-Dist: feather-format (>=0.4.1)
